nbabattle
