Metadata-Version: 2.1
Name: nbabattle
Version: 0.0.7
Summary: A lightweight python library to generate two nba team battle image.
Home-page: https://github.com/cobenash/nba-battle-picture-generator
Author: victor yang
Author-email: victor.yang@hellosanta.com.tw
License: MIT
Project-URL: Bug Tracker, https://github.com/cobenash/nba-battle-picture-generator/issues
Keywords: pypi,nbabattle,nba_battle
Platform: UNKNOWN
Classifier: Development Status :: 3 - Alpha
Classifier: Intended Audience :: Developers
Classifier: Topic :: Software Development :: Documentation
Classifier: License :: OSI Approved :: MIT License
Classifier: Programming Language :: Python :: 3
Classifier: Programming Language :: Python :: 3.7
Classifier: Programming Language :: Python :: 3.8
Classifier: Programming Language :: Python :: 3.9
